simpleswagger/__init__.py
simpleswagger/generator.py
simpleswagger/golang.py
simpleswagger/typescript.py
simpleswagger/templates/base.jinja2
simpleswagger/templates/client.jinja2
simpleswagger/templates/macros.jinja2
simpleswagger/templates/server.jinja2
simpleswagger/templates/validations.jinja2
simpleswagger/templates/typescript/types.jinja2
simple_swagger-0.6.2.dist-info/LICENSE
simple_swagger-0.6.2.dist-info/METADATA
simple_swagger-0.6.2.dist-info/WHEEL
simple_swagger-0.6.2.dist-info/entry_points.txt
simple_swagger-0.6.2.dist-info/top_level.txt
simple_swagger-0.6.2.dist-info/RECORD
