Metadata-Version: 2.1
Name: simple-swagger
Version: 0.6.2
Summary: Simple swagger generator for Go
Home-page: https://github.com/reddec/simple-swagger
Author: Aleksandr Baryshnikov
Author-email: owner@reddec.net
License: MIT
Platform: UNKNOWN
Classifier: Programming Language :: Python :: 3.6
Classifier: License :: OSI Approved :: MIT License
Classifier: Operating System :: OS Independent
Classifier: Intended Audience :: Developers
Classifier: Intended Audience :: System Administrators
Requires-Python: >=3.4
License-File: LICENSE
Requires-Dist: Jinja2 (~=2.11.3)
Requires-Dist: PyYAML (~=5.4.1)
